CHANGELOG.md
LICENSE.txt
MANIFEST.in
Makefile
README.md
requirements.dev.txt
requirements.txt
setup.cfg
setup.py
docs/BuildInfo.md
docs/DefaultApi.md
docs/InlineResponse200.md
docs/InlineResponse422.md
docs/InlineResponseDefault.md
pyskyfiber.egg-info/PKG-INFO
pyskyfiber.egg-info/SOURCES.txt
pyskyfiber.egg-info/dependency_links.txt
pyskyfiber.egg-info/entry_points.txt
pyskyfiber.egg-info/requires.txt
pyskyfiber.egg-info/top_level.txt
skycoin/__init__.py
skycoin/skycoin.py
swig/pyskycoin.i
swig/python_addresses.i
swig/python_basic.i
swig/python_mem.i
swig/python_pubkeys.i
swig/python_seckeys.i
swig/python_sha256s.i
swig/python_skycoin.callback.i
swig/python_skycoin.cipher.crypto.i
swig/python_skycoin.coin.i
swig/python_uxarray.i
swig/structs.i
swig/include/libskycoin.h
tests/utils/__init__.py
tests/utils/transutil.py